mars/__init__.py
mars/calibration.py
mars/cli.py
mars/library.py
mars/matching.py
mars/mzml.py
mars/temperature.py
mars/visualization.py
mars_ms-0.1.3.dist-info/licenses/LICENSE
mars_ms-0.1.3.dist-info/METADATA
mars_ms-0.1.3.dist-info/WHEEL
mars_ms-0.1.3.dist-info/entry_points.txt
mars_ms-0.1.3.dist-info/top_level.txt
mars_ms-0.1.3.dist-info/RECORD
