Metadata-Version: 2.4
Name: mars-ms
Version: 0.1.3
Summary: Mass Accuracy Recalibration System
Author-email: MacCoss Lab <maccoss@uw.edu>
License: MIT
Project-URL: Homepage, https://github.com/maccoss/mars
Project-URL: Repository, https://github.com/maccoss/mars
Classifier: Development Status :: 3 - Alpha
Classifier: Intended Audience :: Science/Research
Classifier: License :: OSI Approved :: MIT License
Classifier: Programming Language :: Python :: 3
Classifier: Programming Language :: Python :: 3.10
Classifier: Programming Language :: Python :: 3.11
Classifier: Programming Language :: Python :: 3.12
Classifier: Topic :: Scientific/Engineering :: Bio-Informatics
Requires-Python: >=3.10
License-File: LICENSE
Requires-Dist: numpy>=1.24
Requires-Dist: pandas>=2.0
Requires-Dist: pyarrow>=14.0
Requires-Dist: pyteomics>=4.6
Requires-Dist: psims>=1.3
Requires-Dist: xgboost>=2.0
Requires-Dist: scikit-learn>=1.3
Requires-Dist: matplotlib>=3.7
Requires-Dist: seaborn>=0.12
Requires-Dist: click>=8.0
Requires-Dist: tqdm>=4.65
Requires-Dist: lxml>=4.9
Provides-Extra: dev
Requires-Dist: pytest>=7.0; extra == "dev"
Requires-Dist: pytest-cov>=4.0; extra == "dev"
Requires-Dist: ruff>=0.1; extra == "dev"
Dynamic: license-file
